reax/__init__.py
reax/_engine.py
reax/_module_hooks.py
reax/exceptions.py
reax/hooks.py
reax/keys.py
reax/modules.py
reax/optimizers.py
reax/plugins.py
reax/random.py
reax/results.py
reax/saving.py
reax/testing.py
reax/types.py
reax/data/__init__.py
reax/data/_datasource_manager.py
reax/data/_datasources.py
reax/data/_loaders.py
reax/data/_types.py
reax/data/collate.py
reax/data/dataloaders.py
reax/data/datamodules.py
reax/data/datasets.py
reax/data/fetchers.py
reax/data/samplers.py
reax/data/utils.py
reax/demos/__init__.py
reax/demos/boring_classes.py
reax/demos/mnist.py
reax/lightning/LICENSE
reax/lightning/__init__.py
reax/lightning/rank_zero.py
reax/listeners/__init__.py
reax/listeners/checkpointer.py
reax/listeners/early_stopping.py
reax/listeners/model_checkpoint.py
reax/listeners/utils.py
reax/listeners/progress/__init__.py
reax/listeners/progress/progress_bar.py
reax/listeners/progress/rich_progress.py
reax/listeners/progress/tqdm_progress.py
reax/loggers/__init__.py
reax/loggers/_utils.py
reax/loggers/csv_logs.py
reax/loggers/logger.py
reax/loggers/mlflow.py
reax/loggers/pandas.py
reax/loggers/tensorboard.py
reax/metrics/__init__.py
reax/metrics/_classification.py
reax/metrics/_globals.py
reax/metrics/_metric.py
reax/metrics/_registry.py
reax/metrics/aggregation.py
reax/metrics/collections.py
reax/metrics/regression.py
reax/metrics/utils.py
reax/metrics/jm/__init__.py
reax/metrics/jm/types.py
reax/metrics/jm/utils.py
reax/stages/__init__.py
reax/stages/common.py
reax/stages/fit.py
reax/stages/predict.py
reax/stages/stages.py
reax/stages/stats.py
reax/stages/test.py
reax/stages/train.py
reax/stages/validation.py
reax/strategies/__init__.py
reax/strategies/_factory.py
reax/strategies/_jax.py
reax/strategies/_parallel.py
reax/strategies/_single_device.py
reax/strategies/_strategies.py
reax/strategies/_utils.py
reax/training/__init__.py
reax/training/_checkpoint_connector.py
reax/training/_checkpointing.py
reax/training/_deprecated.py
reax-0.6.4.dist-info/entry_points.txt
reax-0.6.4.dist-info/licenses/LICENSE.txt
reax-0.6.4.dist-info/WHEEL
reax-0.6.4.dist-info/METADATA
reax-0.6.4.dist-info/RECORD
