Metadata-Version: 2.4
Name: reax
Version: 0.6.4
Summary: REAX: A simple training framework for JAX-based projects
Keywords: machine learning,jax,research
Author-email: Martin Uhrin <martin.uhrin.10@ucl.ac.uk>
Requires-Python: >=3.10
Classifier: Development Status :: 4 - Beta
Classifier: License :: OSI Approved :: GNU Lesser General Public License v3 or later (LGPLv3+)
Classifier: Programming Language :: Python
Classifier: Programming Language :: Python :: 3.10
Classifier: Programming Language :: Python :: 3.11
Classifier: Programming Language :: Python :: 3.12
Classifier: Programming Language :: Python :: 3.13
License-File: LICENSE.txt
Requires-Dist: beartype
Requires-Dist: einops
Requires-Dist: equinox
Requires-Dist: clu
Requires-Dist: flax
Requires-Dist: fsspec
Requires-Dist: jax
Requires-Dist: jaxlib
Requires-Dist: jaxtyping
Requires-Dist: lightning-utilities>=0.10.0
Requires-Dist: optax
Requires-Dist: pytray
Requires-Dist: stevedore
Requires-Dist: tensorboardX
Requires-Dist: tqdm
Requires-Dist: typing-extensions
Requires-Dist: black ; extra == "dev"
Requires-Dist: cloudpickle ; extra == "dev"
Requires-Dist: flit ; extra == "dev"
Requires-Dist: ipython ; extra == "dev"
Requires-Dist: mlflow ; extra == "dev"
Requires-Dist: pandas ; extra == "dev"
Requires-Dist: pytest ; extra == "dev"
Requires-Dist: pytest-cov ; extra == "dev"
Requires-Dist: pytest-env ; extra == "dev"
Requires-Dist: pre-commit ; extra == "dev"
Requires-Dist: pylint ; extra == "dev"
Requires-Dist: docutils ; extra == "docs"
Requires-Dist: jupyter ; extra == "docs"
Requires-Dist: myst-nb ; extra == "docs"
Requires-Dist: pandoc ; extra == "docs"
Requires-Dist: pydata_sphinx_theme ; extra == "docs"
Requires-Dist: scikit-learn ; extra == "docs"
Requires-Dist: sphinx ; extra == "docs"
Requires-Dist: sphinx-autobuild ; extra == "docs"
Requires-Dist: lightning ; extra == "examples"
Requires-Dist: pillow ; extra == "examples"
Requires-Dist: torch ; extra == "examples"
Project-URL: Home, https://github.com/camml-lab/reax
Project-URL: Source, https://github.com/camml-lab/reax
Provides-Extra: dev
Provides-Extra: docs
Provides-Extra: examples
